pixel_mapper.py
circuitpython_pixel_mapper-1.0.4.dist-info/licenses/LICENSE
circuitpython_pixel_mapper-1.0.4.dist-info/METADATA
circuitpython_pixel_mapper-1.0.4.dist-info/WHEEL
circuitpython_pixel_mapper-1.0.4.dist-info/top_level.txt
circuitpython_pixel_mapper-1.0.4.dist-info/RECORD
