Metadata-Version: 2.4
Name: circuitpython-pixel-mapper
Version: 1.0.4
Summary: Pixel Mapper for Adafruit_CircuitPython_LED_Animation
Author-email: CodingFlow <ben@codingflow.dev>
License: MIT
Project-URL: Homepage, https://github.com/clickonben/CircuitPython_pixel_mapper
Keywords: adafruit,blinka,circuitpython,micropython,pixel_mapper,LED,neopixel,ws2812b,animation
Classifier: Intended Audience :: Developers
Classifier: Topic :: Software Development :: Libraries
Classifier: Topic :: Software Development :: Embedded Systems
Classifier: Topic :: System :: Hardware
Classifier: License :: OSI Approved :: MIT License
Classifier: Programming Language :: Python :: 3
License-File: LICENSE
Requires-Dist: Adafruit-Blinka
Provides-Extra: optional
Dynamic: license-file
